circllhist/__init__.py
circllhist/ffi.py
circllhist/wrapper.py
circllhist-0.2.2.dist-info/DESCRIPTION.rst
circllhist-0.2.2.dist-info/METADATA
circllhist-0.2.2.dist-info/RECORD
circllhist-0.2.2.dist-info/WHEEL
circllhist-0.2.2.dist-info/metadata.json
circllhist-0.2.2.dist-info/top_level.txt
