Metadata-Version: 2.0
Name: circllhist
Version: 0.2.2
Summary: Circonus log-linear histogram library
Home-page: https://github.com/circonus-labs/libcircllhist
Author: Heinrich Hartmann
Author-email: heinrich.hartmann@circonus.com
License: UNKNOWN
Platform: UNKNOWN
Requires-Dist: cffi
